<?xml version="1.0" encoding="utf-8" ?><dwsync><file name="alternative_php.html" server="carlosemendoza.com" local="3482589435" remote="318763443849008112" Dst="-1" /><file name="ancillary_classes.html" server="carlosemendoza.com" local="3482589435" remote="318763443849008112" Dst="-1" /><file name="autoloader.html" server="carlosemendoza.com" local="3482589436" remote="318763443849008112" Dst="-1" /><file name="caching.html" server="carlosemendoza.com" local="3482589436" remote="318763443849008112" Dst="-1" /><file name="cli.html" server="carlosemendoza.com" local="3482589436" remote="318763443849008112" Dst="-1" /><file name="common_functions.html" server="carlosemendoza.com" local="3482589436" remote="318763443849008112" Dst="-1" /><file name="controllers.html" server="carlosemendoza.com" local="3482589436" remote="318763443849008112" Dst="-1" /><file name="core_classes.html" server="carlosemendoza.com" local="3482589436" remote="318763443849008112" Dst="-1" /><file name="creating_drivers.html" server="carlosemendoza.com" local="3482589437" remote="318763443849008112" Dst="-1" /><file name="creating_libraries.html" server="carlosemendoza.com" local="3482589437" remote="318763443849008112" Dst="-1" /><file name="credits.html" server="carlosemendoza.com" local="3482589437" remote="318763443849008112" Dst="-1" /><file name="errors.html" server="carlosemendoza.com" local="3482589437" remote="318763443849008112" Dst="-1" /><file name="drivers.html" server="carlosemendoza.com" local="3482589437" remote="318763443849008112" Dst="-1" /><file name="environments.html" server="carlosemendoza.com" local="3482589437" remote="318763443849008112" Dst="-1" /><file name="helpers.html" server="carlosemendoza.com" local="3482589438" remote="318763443849008112" Dst="-1" /><file name="hooks.html" server="carlosemendoza.com" local="3482589438" remote="318763443849008112" Dst="-1" /><file name="libraries.html" server="carlosemendoza.com" local="3482589438" remote="318763443849008112" Dst="-1" /><file name="managing_apps.html" server="carlosemendoza.com" local="3482589438" remote="318763443849008112" Dst="-1" /><file name="models.html" server="carlosemendoza.com" local="3482589438" remote="318763443849008112" Dst="-1" /><file name="profiling.html" server="carlosemendoza.com" local="3482589438" remote="318763443849008112" Dst="-1" /><file name="requirements.html" server="carlosemendoza.com" local="3482589439" remote="318763443849008112" Dst="-1" /><file name="reserved_names.html" server="carlosemendoza.com" local="3482589439" remote="318763443849008112" Dst="-1" /><file name="quick_reference.html" server="carlosemendoza.com" local="3482589439" remote="318763443849008112" Dst="-1" /><file name="security.html" server="carlosemendoza.com" local="3482589439" remote="318763443849008112" Dst="-1" /><file name="styleguide.html" server="carlosemendoza.com" local="3482589439" remote="318763443849008112" Dst="-1" /><file name="routing.html" server="carlosemendoza.com" local="3482589439" remote="318763443849008112" Dst="-1" /><file name="views.html" server="carlosemendoza.com" local="3482589440" remote="318763443849008112" Dst="-1" /><file name="urls.html" server="carlosemendoza.com" local="3482589440" remote="318763443849008112" Dst="-1" /></dwsync>